{
  "slug": "savings-1780229531189",
  "voice": "Leda",
  "speed": 1.3,
  "long": "2026년 5월, 한국은행이 기준금리를 동결했어요. 시중 적금 금리도 4% 후반대에서 멈췄는데요. 이런 상황에서 월급쟁이인 우리는 어떻게 고금리 적금을 찾아야 할까요? 제가 5단계로 딱 정리해 드릴게요. (※ 본 영상의 모든 정보는 2026년 5월 20일 공시 기준 데이터이며, 실제 금리는 변동될 수 있습니다.)\n\n첫 번째, 내게 맞는 적립방식부터 정해야 해요. 매월 같은 금액을 넣는 정액적립식, 자유롭게 넣는 자유적립식이 있는데, 보통 정액이 최고 금리가 좀 더 높은 경우가 많아요.\n\n두 번째, 1금융권과 저축은행 중 어디로 갈지 정하는 거예요. 안정성은 1금융권, 높은 최고 금리는 저축은행이죠. 2026년 5월 20일 공시 기준 데이터로 보면, 1금융권에서는 경남은행의 '오면우대! 하면우대! 정기적금'이 최고 연 7%까지 보이는 상품이 있고요. 저축은행에서는 웰컴저축은행의 '웰뱅 라이킷 적금'이 무려 최고 연 14%까지 나오는 상품도 있습니다. 물론 우대조건을 다 채웠을 때 이야기이고, 가입 직전 반드시 확인해야 해요!\n\n세 번째, 바로 이 우대조건을 꼼꼼히 확인하는 거예요. 급여이체, 카드 실적, 자동이체, 심지어 걸음수까지! 내가 달성 가능한 조건인지 꼭 봐야 해요. 최고 금리만 보고 가입했다가 후회한 적 저도 많거든요.\n\n네 번째는 월 한도와 가입 방법이에요. 고금리 상품은 월 한도가 20~30만원으로 제한되는 경우가 많고, 스마트폰 앱으로만 가입 가능한 상품도 많으니 미리 체크하세요.\n\n마지막으로, 중도해지는 절대 피해야 해요. 이자가 확 줄어들거든요. 모든 정보는 2026년 5월 20일 공시 기준 데이터이며, 실제 금리는 변동될 수 있으니 꼭 가입 직전 확인하세요!\n\n자세한 상품 정보와 우대조건은 제 블로그에서 확인하시고, 이웃 추가로 매주 재테크 정보 받아보세요!",
  "short": "2026년 5월, 기준금리 동결! 고금리 적금, 월급쟁이는 어떻게 골라야 할까요?\n\n2026년 5월 20일 공시 기준 데이터로 핵심만 알려드릴게요!\n1금융권은 경남은행 적금이 최고 연 7%까지 보이는 상품도 있고요!\n저축은행은 웰컴저축은행 '웰뱅 라이킷 적금'이 무려 최고 연 14%까지 가능해요.\n\n하지만 최고 금리는 우대조건 충족 시! 급여이체, 카드 실적, 자동이체 등 내가 채울 수 있는 조건인지 꼭 확인해야 후회 없어요.\n\n모든 금리와 조건은 2026년 5월 20일 공시 기준 데이터이며 변동될 수 있으니, 자세한 정보는 제 블로그에서 가입 직전 꼭 확인하세요!"
}